sage_sws2rst/__init__.py
sage_sws2rst/comments2rst.py
sage_sws2rst/results2rst.py
sage_sws2rst/worksheet2rst.py
sage_sws2rst-10.6.data/scripts/sage-sws2rst
sage_sws2rst-10.6.dist-info/METADATA
sage_sws2rst-10.6.dist-info/WHEEL
sage_sws2rst-10.6.dist-info/top_level.txt
sage_sws2rst-10.6.dist-info/RECORD
