Metadata-Version: 2.1
Name: sage-sws2rst
Version: 10.6
Summary: Sage: Open Source Mathematics Software: SageNB worksheet converter
Author-email: The Sage Developers <sage-support@googlegroups.com>
License: GNU General Public License (GPL) v3 or later
Project-URL: Homepage, https://www.sagemath.org
